wikiman/__init__.py
wikiman/wikiman.py
wikiman-0.3.0.dist-info/LICENSE
wikiman-0.3.0.dist-info/METADATA
wikiman-0.3.0.dist-info/WHEEL
wikiman-0.3.0.dist-info/entry_points.txt
wikiman-0.3.0.dist-info/top_level.txt
wikiman-0.3.0.dist-info/RECORD
