Metadata-Version: 2.1
Name: wikiman
Version: 0.3.0
Summary: GitHub Wiki CLI manager.
Home-page: https://github.com/blakeNaccarato/wikiman
Author: Blake Naccarato
License: UNKNOWN
Platform: UNKNOWN
Requires-Python: >=3.6
Requires-Dist: fire
Requires-Dist: markdown
Requires-Dist: GitPython
